nNeuron/__init__.py
nNeuron/perceptron.py
nNeuron_pypi_Datadriven1-0.0.1.dist-info/LICENSE
nNeuron_pypi_Datadriven1-0.0.1.dist-info/METADATA
nNeuron_pypi_Datadriven1-0.0.1.dist-info/WHEEL
nNeuron_pypi_Datadriven1-0.0.1.dist-info/top_level.txt
nNeuron_pypi_Datadriven1-0.0.1.dist-info/RECORD
