Metadata-Version: 2.1
Name: nNeuron-pypi-Datadriven1
Version: 0.0.1
Summary: its an implimentation of Perceptron
Home-page: https://github.com/Datadriven1/nNeuron_pypi
Author: Datadriven1
Author-email: bhupendra.patel147@gmail.com
License: UNKNOWN
Project-URL: Bug Tracker, https://github.com/Datadriven1/nNeuron_pypi/issues
Platform: UNKNOWN
Classifier: Programming Language :: Python :: 3
Classifier: License :: OSI Approved :: MIT License
Classifier: Operating System :: OS Independent
Requires-Python: >=3.7
License-File: LICENSE
Requires-Dist: numpy
Requires-Dist: tqdm
